odoo8_addon_donation_bank_statement-8.0.0.1.0-py2.7-nspkg.pth
odoo_addons/donation_bank_statement/demo.xml
odoo_addons/donation_bank_statement/__openerp__.py
odoo_addons/donation_bank_statement/bank_statement_view.xml
odoo_addons/donation_bank_statement/donation_view.xml
odoo_addons/donation_bank_statement/__init__.py
odoo_addons/donation_bank_statement/company.py
odoo_addons/donation_bank_statement/README.rst
odoo_addons/donation_bank_statement/donation.py
odoo_addons/donation_bank_statement/company_view.xml
odoo_addons/donation_bank_statement/bank_statement.py
odoo_addons/donation_bank_statement/security/ir.model.access.csv
odoo_addons/donation_bank_statement/i18n/donation_bank_statement.pot
odoo_addons/donation_bank_statement/i18n/fr.po
odoo_addons/donation_bank_statement/static/description/icon.png
odoo8_addon_donation_bank_statement-8.0.0.1.0.dist-info/top_level.txt
odoo8_addon_donation_bank_statement-8.0.0.1.0.dist-info/WHEEL
odoo8_addon_donation_bank_statement-8.0.0.1.0.dist-info/RECORD
odoo8_addon_donation_bank_statement-8.0.0.1.0.dist-info/metadata.json
odoo8_addon_donation_bank_statement-8.0.0.1.0.dist-info/DESCRIPTION.rst
odoo8_addon_donation_bank_statement-8.0.0.1.0.dist-info/METADATA
odoo8_addon_donation_bank_statement-8.0.0.1.0.dist-info/namespace_packages.txt
