Metadata-Version: 2.0
Name: odoo8-addon-donation-bank-statement
Version: 8.0.0.1.0
Summary: Creates donation from unreconciled bank statement lines
Home-page: http://www.barroux.org
Author: UNKNOWN
Author-email: UNKNOWN
License: AGPL-3
Platform: UNKNOWN
Requires-Dist: odoo (<9.0a,>=8.0a)
Requires-Dist: odoo8-addon-donation
Classifier: Programming Language :: Python :: 2.7
Classifier: Framework :: Odoo
Classifier: License :: OSI Approved :: GNU Affero General Public License v3
